LICENSE
MANIFEST.in
README
setup.cfg
setup.py
yanky/__init__.py
yanky.egg-info/PKG-INFO
yanky.egg-info/SOURCES.txt
yanky.egg-info/dependency_links.txt
yanky.egg-info/top_level.txt