Metadata-Version: 1.1
Name: yanky
Version: 0.9.0
Summary: Easy and Simple copy and paste module for GNU/Linux systems
Home-page: https://github.com/noahfx/yanky
Author: Josue Ortega
Author-email: josueortega@protonmail.ch
License: MIT
Keywords: yannk copy paste api xsel xclip clipboard
Platform: UNKNOWN
Classifier: Development Status :: 3 - Alpha
Classifier: License :: OSI Approved :: MIT License
Classifier: Operating System :: POSIX
Classifier: Programming Language :: Python :: 3
Classifier: Programming Language :: Python :: 3.1
Classifier: Programming Language :: Python :: 3.2
Classifier: Programming Language :: Python :: 3.3
Classifier: Programming Language :: Python :: 3.4
Classifier: Programming Language :: Python :: 3.5
Classifier: Intended Audience :: Developers
